[
    {
        "username": "FP1",
        "userAge": 27,
        "usergender": "male",
        "inputtechnique": "BareHandIntenSelect",
        "radius": 0.21,
        "distance": 0.75,
        "spacing": 0.7,
        "clickDuration": 1.6602852761818183,
        "isCorrect": 0.7272727272727273,
        "HeisenbergError": 0.2727272727272727,
        "HeisenbergAngle": 1.9306492263135604,
        "EffectiveScore": 0.4380408220840497
    },
    {
        "username": "FP1",
        "userAge": 27,
        "usergender": "male",
        "inputtechnique": "BareHandIntenSelect",
        "radius": 0.21,
        "distance": 0.75,
        "spacing": 0.3,
        "clickDuration": 2.4382623992777774,
        "isCorrect": 0.4444444444444444,
        "HeisenbergError": 0.4444444444444444,
        "HeisenbergAngle": 1.8300964015242565,
        "EffectiveScore": 0.18227916920512352
    },
    {
        "username": "FP1",
        "userAge": 27,
        "usergender": "male",
        "inputtechnique": "BareHandIntenSelect",
        "radius": 0.21,
        "distance": 0.75,
        "spacing": 0.5,
        "clickDuration": 0.8848345716000001,
        "isCorrect": 0.8,
        "HeisenbergError": 0.2,
        "HeisenbergAngle": 1.3275640215868647,
        "EffectiveScore": 0.9041238053723442
    },
    {
        "username": "FP1",
        "userAge": 27,
        "usergender": "male",
        "inputtechnique": "BareHandIntenSelect",
        "radius": 0.21,
        "distance": 0.75,
        "spacing": 0.5,
        "clickDuration": 3.9025571853,
        "isCorrect": 0.8,
        "HeisenbergError": 0.1,
        "HeisenbergAngle": 1.0837460507230663,
        "EffectiveScore": 0.20499379304764803
    },
    {
        "username": "FP1",
        "userAge": 27,
        "usergender": "male",
        "inputtechnique": "BareHandIntenSelect",
        "radius": 0.21,
        "distance": 0.75,
        "spacing": 0.3,
        "clickDuration": 1.0900338169166666,
        "isCorrect": 0.6666666666666666,
        "HeisenbergError": 0.3333333333333333,
        "HeisenbergAngle": 0.541214460278903,
        "EffectiveScore": 0.6116018203475916
    },
    {
        "username": "FP1",
        "userAge": 27,
        "usergender": "male",
        "inputtechnique": "BareHandIntenSelect",
        "radius": 0.21,
        "distance": 0.75,
        "spacing": 0.7,
        "clickDuration": 1.1579093729999999,
        "isCorrect": 0.6153846153846154,
        "HeisenbergError": 0.23076923076923078,
        "HeisenbergAngle": 1.5124049383531475,
        "EffectiveScore": 0.5314618136221059
    },
    {
        "username": "FP1",
        "userAge": 27,
        "usergender": "male",
        "inputtechnique": "BareHandIntenSelect",
        "radius": 0.21,
        "distance": 0.75,
        "spacing": 0.5,
        "clickDuration": 1.6954535033333333,
        "isCorrect": 0.5333333333333333,
        "HeisenbergError": 0.4666666666666667,
        "HeisenbergAngle": 0.7032638212123227,
        "EffectiveScore": 0.31456677065149674
    },
    {
        "username": "FP1",
        "userAge": 27,
        "usergender": "male",
        "inputtechnique": "BareHandIntenSelect",
        "radius": 0.21,
        "distance": 0.75,
        "spacing": 0.7,
        "clickDuration": 1.843178714,
        "isCorrect": 0.8,
        "HeisenbergError": 0.1,
        "HeisenbergAngle": 1.5362920162757203,
        "EffectiveScore": 0.4340327901594897
    },
    {
        "username": "FP1",
        "userAge": 27,
        "usergender": "male",
        "inputtechnique": "BareHandIntenSelect",
        "radius": 0.21,
        "distance": 0.75,
        "spacing": 0.3,
        "clickDuration": 1.7791553982142858,
        "isCorrect": 0.5714285714285714,
        "HeisenbergError": 0.2857142857142857,
        "HeisenbergAngle": 2.185370675798094,
        "EffectiveScore": 0.3211796855980689
    },
    {
        "username": "FP10",
        "userAge": 25,
        "usergender": "male",
        "inputtechnique": "BareHandIntenSelect",
        "radius": 0.21,
        "distance": 0.75,
        "spacing": 0.5,
        "clickDuration": 1.4243881499999997,
        "isCorrect": 1.0,
        "HeisenbergError": 0.0,
        "HeisenbergAngle": 0.38744987326827984,
        "EffectiveScore": 0.7020558265666561
    },
    {
        "username": "FP10",
        "userAge": 25,
        "usergender": "male",
        "inputtechnique": "BareHandIntenSelect",
        "radius": 0.21,
        "distance": 0.75,
        "spacing": 0.7,
        "clickDuration": 0.8908884753749999,
        "isCorrect": 0.75,
        "HeisenbergError": 0.125,
        "HeisenbergAngle": 1.3966568533792967,
        "EffectiveScore": 0.8418562151500545
    },
    {
        "username": "FP10",
        "userAge": 25,
        "usergender": "male",
        "inputtechnique": "BareHandIntenSelect",
        "radius": 0.21,
        "distance": 0.75,
        "spacing": 0.3,
        "clickDuration": 1.043224014875,
        "isCorrect": 0.75,
        "HeisenbergError": 0.25,
        "HeisenbergAngle": 0.6991699396389082,
        "EffectiveScore": 0.718925167850805
    },
    {
        "username": "FP10",
        "userAge": 25,
        "usergender": "male",
        "inputtechnique": "BareHandIntenSelect",
        "radius": 0.21,
        "distance": 0.75,
        "spacing": 0.7,
        "clickDuration": 1.034421903,
        "isCorrect": 0.8571428571428571,
        "HeisenbergError": 0.14285714285714285,
        "HeisenbergAngle": 0.8499852807852868,
        "EffectiveScore": 0.8286201738932603
    },
    {
        "username": "FP10",
        "userAge": 25,
        "usergender": "male",
        "inputtechnique": "BareHandIntenSelect",
        "radius": 0.21,
        "distance": 0.75,
        "spacing": 0.5,
        "clickDuration": 0.8485916358888889,
        "isCorrect": 0.6666666666666666,
        "HeisenbergError": 0.1111111111111111,
        "HeisenbergAngle": 1.4328061993263672,
        "EffectiveScore": 0.785615410842863
    },
    {
        "username": "FP10",
        "userAge": 25,
        "usergender": "male",
        "inputtechnique": "BareHandIntenSelect",
        "radius": 0.21,
        "distance": 0.75,
        "spacing": 0.3,
        "clickDuration": 0.9428043392000001,
        "isCorrect": 0.6,
        "HeisenbergError": 0.4,
        "HeisenbergAngle": 0.7668422247028228,
        "EffectiveScore": 0.6363992771916168
    },
    {
        "username": "FP10",
        "userAge": 25,
        "usergender": "male",
        "inputtechnique": "BareHandIntenSelect",
        "radius": 0.21,
        "distance": 0.75,
        "spacing": 0.3,
        "clickDuration": 1.7831191986666666,
        "isCorrect": 0.6666666666666666,
        "HeisenbergError": 0.2222222222222222,
        "HeisenbergAngle": 0.43382205830269654,
        "EffectiveScore": 0.37387666913416046
    },
    {
        "username": "FP10",
        "userAge": 25,
        "usergender": "male",
        "inputtechnique": "BareHandIntenSelect",
        "radius": 0.21,
        "distance": 0.75,
        "spacing": 0.5,
        "clickDuration": 1.2929530868571428,
        "isCorrect": 0.8571428571428571,
        "HeisenbergError": 0.14285714285714285,
        "HeisenbergAngle": 0.491790279905573,
        "EffectiveScore": 0.6629342285158734
    },
    {
        "username": "FP10",
        "userAge": 25,
        "usergender": "male",
        "inputtechnique": "BareHandIntenSelect",
        "radius": 0.21,
        "distance": 0.75,
        "spacing": 0.7,
        "clickDuration": 1.4058837687499999,
        "isCorrect": 0.5,
        "HeisenbergError": 0.4166666666666667,
        "HeisenbergAngle": 1.2595910574044675,
        "EffectiveScore": 0.355648177405562
    },
    {
        "username": "FP11",
        "userAge": 25,
        "usergender": "female",
        "inputtechnique": "BareHandIntenSelect",
        "radius": 0.21,
        "distance": 0.75,
        "spacing": 0.5,
        "clickDuration": 1.2410850422222224,
        "isCorrect": 0.6666666666666666,
        "HeisenbergError": 0.1111111111111111,
        "HeisenbergAngle": 0.4902717298858463,
        "EffectiveScore": 0.5371643714865566
    },
    {
        "username": "FP11",
        "userAge": 25,
        "usergender": "female",
        "inputtechnique": "BareHandIntenSelect",
        "radius": 0.21,
        "distance": 0.75,
        "spacing": 0.7,
        "clickDuration": 1.1385967538333333,
        "isCorrect": 1.0,
        "HeisenbergError": 0.0,
        "HeisenbergAngle": 0.9035216130035212,
        "EffectiveScore": 0.8782740655401333
    },
    {
        "username": "FP11",
        "userAge": 25,
        "usergender": "female",
        "inputtechnique": "BareHandIntenSelect",
        "radius": 0.21,
        "distance": 0.75,
        "spacing": 0.3,
        "clickDuration": 1.2847316988750002,
        "isCorrect": 0.75,
        "HeisenbergError": 0.25,
        "HeisenbergAngle": 0.5323714452664859,
        "EffectiveScore": 0.583779477580223
    },
    {
        "username": "FP11",
        "userAge": 25,
        "usergender": "female",
        "inputtechnique": "BareHandIntenSelect",
        "radius": 0.21,
        "distance": 0.75,
        "spacing": 0.3,
        "clickDuration": 1.3645965505454545,
        "isCorrect": 0.5454545454545454,
        "HeisenbergError": 0.2727272727272727,
        "HeisenbergAngle": 0.496141484129196,
        "EffectiveScore": 0.39971854335738805
    },
    {
        "username": "FP11",
        "userAge": 25,
        "usergender": "female",
        "inputtechnique": "BareHandIntenSelect",
        "radius": 0.21,
        "distance": 0.75,
        "spacing": 0.7,
        "clickDuration": 1.359688,
        "isCorrect": 0.8571428571428571,
        "HeisenbergError": 0.0,
        "HeisenbergAngle": 0.5174376833907404,
        "EffectiveScore": 0.6303967212646262
    },
    {
        "username": "FP11",
        "userAge": 25,
        "usergender": "female",
        "inputtechnique": "BareHandIntenSelect",
        "radius": 0.21,
        "distance": 0.75,
        "spacing": 0.5,
        "clickDuration": 1.08551667,
        "isCorrect": 0.75,
        "HeisenbergError": 0.25,
        "HeisenbergAngle": 0.6661230424294621,
        "EffectiveScore": 0.6909152302562059
    },
    {
        "username": "FP11",
        "userAge": 25,
        "usergender": "female",
        "inputtechnique": "BareHandIntenSelect",
        "radius": 0.21,
        "distance": 0.75,
        "spacing": 0.5,
        "clickDuration": 1.2656157972500002,
        "isCorrect": 0.75,
        "HeisenbergError": 0.125,
        "HeisenbergAngle": 0.5021810116408567,
        "EffectiveScore": 0.592596901547564
    },
    {
        "username": "FP11",
        "userAge": 25,
        "usergender": "female",
        "inputtechnique": "BareHandIntenSelect",
        "radius": 0.21,
        "distance": 0.75,
        "spacing": 0.7,
        "clickDuration": 0.8794318171666667,
        "isCorrect": 1.0,
        "HeisenbergError": 0.0,
        "HeisenbergAngle": 0.4218089509733233,
        "EffectiveScore": 1.1370978175679123
    },
    {
        "username": "FP11",
        "userAge": 25,
        "usergender": "female",
        "inputtechnique": "BareHandIntenSelect",
        "radius": 0.21,
        "distance": 0.75,
        "spacing": 0.3,
        "clickDuration": 1.1490063726250002,
        "isCorrect": 0.75,
        "HeisenbergError": 0.125,
        "HeisenbergAngle": 0.36629027737915193,
        "EffectiveScore": 0.6527378941219995
    },
    {
        "username": "FP12",
        "userAge": 25,
        "usergender": "female",
        "inputtechnique": "BareHandIntenSelect",
        "radius": 0.21,
        "distance": 0.75,
        "spacing": 0.3,
        "clickDuration": 1.182602347375,
        "isCorrect": 0.75,
        "HeisenbergError": 0.0,
        "HeisenbergAngle": 0.5654713093842932,
        "EffectiveScore": 0.6341945808451681
    },
    {
        "username": "FP12",
        "userAge": 25,
        "usergender": "female",
        "inputtechnique": "BareHandIntenSelect",
        "radius": 0.21,
        "distance": 0.75,
        "spacing": 0.5,
        "clickDuration": 1.0300936215714285,
        "isCorrect": 0.8571428571428571,
        "HeisenbergError": 0.14285714285714285,
        "HeisenbergAngle": 0.9362612734579858,
        "EffectiveScore": 0.8321018975297299
    },
    {
        "username": "FP12",
        "userAge": 25,
        "usergender": "female",
        "inputtechnique": "BareHandIntenSelect",
        "radius": 0.21,
        "distance": 0.75,
        "spacing": 0.7,
        "clickDuration": 1.16888721475,
        "isCorrect": 0.75,
        "HeisenbergError": 0.125,
        "HeisenbergAngle": 1.9072149792945832,
        "EffectiveScore": 0.641635899970391
    },
    {
        "username": "FP12",
        "userAge": 25,
        "usergender": "female",
        "inputtechnique": "BareHandIntenSelect",
        "radius": 0.21,
        "distance": 0.75,
        "spacing": 0.3,
        "clickDuration": 1.940252497666667,
        "isCorrect": 0.4,
        "HeisenbergError": 0.3333333333333333,
        "HeisenbergAngle": 0.49584955547806225,
        "EffectiveScore": 0.20615873474253324
    },
    {
        "username": "FP12",
        "userAge": 25,
        "usergender": "female",
        "inputtechnique": "BareHandIntenSelect",
        "radius": 0.21,
        "distance": 0.75,
        "spacing": 0.5,
        "clickDuration": 1.7846504435000001,
        "isCorrect": 0.75,
        "HeisenbergError": 0.0,
        "HeisenbergAngle": 1.2871433757732302,
        "EffectiveScore": 0.4202503648440664
    },
    {
        "username": "FP12",
        "userAge": 25,
        "usergender": "female",
        "inputtechnique": "BareHandIntenSelect",
        "radius": 0.21,
        "distance": 0.75,
        "spacing": 0.7,
        "clickDuration": 3.1136110775,
        "isCorrect": 0.75,
        "HeisenbergError": 0.125,
        "HeisenbergAngle": 1.1502889036177812,
        "EffectiveScore": 0.24087786860078708
    },
    {
        "username": "FP12",
        "userAge": 25,
        "usergender": "female",
        "inputtechnique": "BareHandIntenSelect",
        "radius": 0.21,
        "distance": 0.75,
        "spacing": 0.5,
        "clickDuration": 2.1651862269999995,
        "isCorrect": 0.6,
        "HeisenbergError": 0.1,
        "HeisenbergAngle": 0.8698546038959236,
        "EffectiveScore": 0.2771124222563236
    },
    {
        "username": "FP12",
        "userAge": 25,
        "usergender": "female",
        "inputtechnique": "BareHandIntenSelect",
        "radius": 0.21,
        "distance": 0.75,
        "spacing": 0.3,
        "clickDuration": 2.4629732143,
        "isCorrect": 0.6,
        "HeisenbergError": 0.3,
        "HeisenbergAngle": 0.6658728865707044,
        "EffectiveScore": 0.2436080086118702
    },
    {
        "username": "FP12",
        "userAge": 25,
        "usergender": "female",
        "inputtechnique": "BareHandIntenSelect",
        "radius": 0.21,
        "distance": 0.75,
        "spacing": 0.7,
        "clickDuration": 2.5046430733333334,
        "isCorrect": 0.6666666666666666,
        "HeisenbergError": 0.2222222222222222,
        "HeisenbergAngle": 1.6799216299926447,
        "EffectiveScore": 0.266172323619519
    },
    {
        "username": "FP13",
        "userAge": 23,
        "usergender": "male",
        "inputtechnique": "BareHandIntenSelect",
        "radius": 0.21,
        "distance": 0.75,
        "spacing": 0.3,
        "clickDuration": 2.5187894972727274,
        "isCorrect": 0.5454545454545454,
        "HeisenbergError": 0.36363636363636365,
        "HeisenbergAngle": 0.6343952921670728,
        "EffectiveScore": 0.2165542400606116
    },
    {
        "username": "FP13",
        "userAge": 23,
        "usergender": "male",
        "inputtechnique": "BareHandIntenSelect",
        "radius": 0.21,
        "distance": 0.75,
        "spacing": 0.5,
        "clickDuration": 1.7933375085714285,
        "isCorrect": 0.8571428571428571,
        "HeisenbergError": 0.14285714285714285,
        "HeisenbergAngle": 0.4128497519303641,
        "EffectiveScore": 0.47795958822366713
    },
    {
        "username": "FP13",
        "userAge": 23,
        "usergender": "male",
        "inputtechnique": "BareHandIntenSelect",
        "radius": 0.21,
        "distance": 0.75,
        "spacing": 0.7,
        "clickDuration": 1.2071578187500003,
        "isCorrect": 0.75,
        "HeisenbergError": 0.25,
        "HeisenbergAngle": 1.474768968301406,
        "EffectiveScore": 0.6212940746857917
    },
    {
        "username": "FP13",
        "userAge": 23,
        "usergender": "male",
        "inputtechnique": "BareHandIntenSelect",
        "radius": 0.21,
        "distance": 0.75,
        "spacing": 0.3,
        "clickDuration": 2.245239161,
        "isCorrect": 0.8571428571428571,
        "HeisenbergError": 0.14285714285714285,
        "HeisenbergAngle": 0.5042771088976908,
        "EffectiveScore": 0.3817601581299236
    },
    {
        "username": "FP13",
        "userAge": 23,
        "usergender": "male",
        "inputtechnique": "BareHandIntenSelect",
        "radius": 0.21,
        "distance": 0.75,
        "spacing": 0.5,
        "clickDuration": 1.27069033425,
        "isCorrect": 0.75,
        "HeisenbergError": 0.25,
        "HeisenbergAngle": 0.4521074042585049,
        "EffectiveScore": 0.5902303494286614
    },
    {
        "username": "FP13",
        "userAge": 23,
        "usergender": "male",
        "inputtechnique": "BareHandIntenSelect",
        "radius": 0.21,
        "distance": 0.75,
        "spacing": 0.7,
        "clickDuration": 1.1154092847,
        "isCorrect": 0.6,
        "HeisenbergError": 0.3,
        "HeisenbergAngle": 0.41856444417311023,
        "EffectiveScore": 0.537919137154552
    },
    {
        "username": "FP13",
        "userAge": 23,
        "usergender": "male",
        "inputtechnique": "BareHandIntenSelect",
        "radius": 0.21,
        "distance": 0.75,
        "spacing": 0.5,
        "clickDuration": 1.4607148537777777,
        "isCorrect": 0.6666666666666666,
        "HeisenbergError": 0.1111111111111111,
        "HeisenbergAngle": 0.7212155183146359,
        "EffectiveScore": 0.4563975405209978
    },
    {
        "username": "FP13",
        "userAge": 23,
        "usergender": "male",
        "inputtechnique": "BareHandIntenSelect",
        "radius": 0.21,
        "distance": 0.75,
        "spacing": 0.7,
        "clickDuration": 1.5795316014285716,
        "isCorrect": 0.8571428571428571,
        "HeisenbergError": 0.14285714285714285,
        "HeisenbergAngle": 0.2877945583657979,
        "EffectiveScore": 0.5426563522804062
    },
    {
        "username": "FP13",
        "userAge": 23,
        "usergender": "male",
        "inputtechnique": "BareHandIntenSelect",
        "radius": 0.21,
        "distance": 0.75,
        "spacing": 0.3,
        "clickDuration": 2.6701230149090907,
        "isCorrect": 0.5454545454545454,
        "HeisenbergError": 0.2727272727272727,
        "HeisenbergAngle": 0.5634204963101898,
        "EffectiveScore": 0.20428068010683637
    },
    {
        "username": "FP14",
        "userAge": 25,
        "usergender": "male",
        "inputtechnique": "BareHandIntenSelect",
        "radius": 0.21,
        "distance": 0.75,
        "spacing": 0.7,
        "clickDuration": 1.4385631795,
        "isCorrect": 0.75,
        "HeisenbergError": 0.125,
        "HeisenbergAngle": 1.0738236720822947,
        "EffectiveScore": 0.5213535357276952
    },
    {
        "username": "FP14",
        "userAge": 25,
        "usergender": "male",
        "inputtechnique": "BareHandIntenSelect",
        "radius": 0.21,
        "distance": 0.75,
        "spacing": 0.5,
        "clickDuration": 1.2964096051818181,
        "isCorrect": 0.5454545454545454,
        "HeisenbergError": 0.45454545454545453,
        "HeisenbergAngle": 0.8670655393622897,
        "EffectiveScore": 0.4207424438035129
    },
    {
        "username": "FP14",
        "userAge": 25,
        "usergender": "male",
        "inputtechnique": "BareHandIntenSelect",
        "radius": 0.21,
        "distance": 0.75,
        "spacing": 0.3,
        "clickDuration": 1.35554193175,
        "isCorrect": 0.75,
        "HeisenbergError": 0.125,
        "HeisenbergAngle": 0.39048032159342067,
        "EffectiveScore": 0.5532842492240373
    },
    {
        "username": "FP14",
        "userAge": 25,
        "usergender": "male",
        "inputtechnique": "BareHandIntenSelect",
        "radius": 0.21,
        "distance": 0.75,
        "spacing": 0.7,
        "clickDuration": 1.3672514633333333,
        "isCorrect": 1.0,
        "HeisenbergError": 0.0,
        "HeisenbergAngle": 0.7541715809936891,
        "EffectiveScore": 0.7313943534293383
    },
    {
        "username": "FP14",
        "userAge": 25,
        "usergender": "male",
        "inputtechnique": "BareHandIntenSelect",
        "radius": 0.21,
        "distance": 0.75,
        "spacing": 0.5,
        "clickDuration": 1.0968913921428574,
        "isCorrect": 0.8571428571428571,
        "HeisenbergError": 0.14285714285714285,
        "HeisenbergAngle": 0.9734232117687087,
        "EffectiveScore": 0.7814291034487616
    },
    {
        "username": "FP14",
        "userAge": 25,
        "usergender": "male",
        "inputtechnique": "BareHandIntenSelect",
        "radius": 0.21,
        "distance": 0.75,
        "spacing": 0.3,
        "clickDuration": 1.2780200612222221,
        "isCorrect": 0.6666666666666666,
        "HeisenbergError": 0.2222222222222222,
        "HeisenbergAngle": 0.5327927776357786,
        "EffectiveScore": 0.521640220599594
    },
    {
        "username": "FP14",
        "userAge": 25,
        "usergender": "male",
        "inputtechnique": "BareHandIntenSelect",
        "radius": 0.21,
        "distance": 0.75,
        "spacing": 0.5,
        "clickDuration": 1.390829312,
        "isCorrect": 0.6,
        "HeisenbergError": 0.1,
        "HeisenbergAngle": 0.669201512973987,
        "EffectiveScore": 0.43139729284048917
    },
    {
        "username": "FP14",
        "userAge": 25,
        "usergender": "male",
        "inputtechnique": "BareHandIntenSelect",
        "radius": 0.21,
        "distance": 0.75,
        "spacing": 0.7,
        "clickDuration": 1.263825534714286,
        "isCorrect": 0.8571428571428571,
        "HeisenbergError": 0.14285714285714285,
        "HeisenbergAngle": 0.7339910387117559,
        "EffectiveScore": 0.6782129602537522
    },
    {
        "username": "FP14",
        "userAge": 25,
        "usergender": "male",
        "inputtechnique": "BareHandIntenSelect",
        "radius": 0.21,
        "distance": 0.75,
        "spacing": 0.3,
        "clickDuration": 1.6321861746666668,
        "isCorrect": 1.0,
        "HeisenbergError": 0.0,
        "HeisenbergAngle": 0.27822955579605646,
        "EffectiveScore": 0.6126752055133814
    },
    {
        "username": "FP15",
        "userAge": 25,
        "usergender": "female",
        "inputtechnique": "BareHandIntenSelect",
        "radius": 0.21,
        "distance": 0.75,
        "spacing": 0.7,
        "clickDuration": 1.9164791371428573,
        "isCorrect": 0.8571428571428571,
        "HeisenbergError": 0.0,
        "HeisenbergAngle": 0.3419506553126972,
        "EffectiveScore": 0.4472487284263947
    },
    {
        "username": "FP15",
        "userAge": 25,
        "usergender": "female",
        "inputtechnique": "BareHandIntenSelect",
        "radius": 0.21,
        "distance": 0.75,
        "spacing": 0.3,
        "clickDuration": 2.5607393785714287,
        "isCorrect": 0.8571428571428571,
        "HeisenbergError": 0.0,
        "HeisenbergAngle": 0.12588318867510856,
        "EffectiveScore": 0.33472475345032393
    },
    {
        "username": "FP15",
        "userAge": 25,
        "usergender": "female",
        "inputtechnique": "BareHandIntenSelect",
        "radius": 0.21,
        "distance": 0.75,
        "spacing": 0.5,
        "clickDuration": 1.7742698068333336,
        "isCorrect": 1.0,
        "HeisenbergError": 0.0,
        "HeisenbergAngle": 0.5169979423804425,
        "EffectiveScore": 0.5636121384406421
    },
    {
        "username": "FP15",
        "userAge": 25,
        "usergender": "female",
        "inputtechnique": "BareHandIntenSelect",
        "radius": 0.21,
        "distance": 0.75,
        "spacing": 0.3,
        "clickDuration": 1.603072474909091,
        "isCorrect": 0.5454545454545454,
        "HeisenbergError": 0.2727272727272727,
        "HeisenbergAngle": 0.18334083749150415,
        "EffectiveScore": 0.3402556989729848
    },
    {
        "username": "FP15",
        "userAge": 25,
        "usergender": "female",
        "inputtechnique": "BareHandIntenSelect",
        "radius": 0.21,
        "distance": 0.75,
        "spacing": 0.5,
        "clickDuration": 1.4448677985714287,
        "isCorrect": 0.8571428571428571,
        "HeisenbergError": 0.0,
        "HeisenbergAngle": 0.8963965565425985,
        "EffectiveScore": 0.593232722045804
    },
    {
        "username": "FP15",
        "userAge": 25,
        "usergender": "female",
        "inputtechnique": "BareHandIntenSelect",
        "radius": 0.21,
        "distance": 0.75,
        "spacing": 0.7,
        "clickDuration": 1.3715633833333334,
        "isCorrect": 1.0,
        "HeisenbergError": 0.0,
        "HeisenbergAngle": 0.31604107915881124,
        "EffectiveScore": 0.7290949963753649
    },
    {
        "username": "FP15",
        "userAge": 25,
        "usergender": "female",
        "inputtechnique": "BareHandIntenSelect",
        "radius": 0.21,
        "distance": 0.75,
        "spacing": 0.5,
        "clickDuration": 1.4947652185714284,
        "isCorrect": 0.8571428571428571,
        "HeisenbergError": 0.14285714285714285,
        "HeisenbergAngle": 0.3514647015187165,
        "EffectiveScore": 0.5734297577261281
    },
    {
        "username": "FP15",
        "userAge": 25,
        "usergender": "female",
        "inputtechnique": "BareHandIntenSelect",
        "radius": 0.21,
        "distance": 0.75,
        "spacing": 0.3,
        "clickDuration": 1.7618156449999998,
        "isCorrect": 1.0,
        "HeisenbergError": 0.0,
        "HeisenbergAngle": 0.4238814675345564,
        "EffectiveScore": 0.5675962765105314
    },
    {
        "username": "FP15",
        "userAge": 25,
        "usergender": "female",
        "inputtechnique": "BareHandIntenSelect",
        "radius": 0.21,
        "distance": 0.75,
        "spacing": 0.7,
        "clickDuration": 0.999748034,
        "isCorrect": 0.75,
        "HeisenbergError": 0.25,
        "HeisenbergAngle": 1.1430539219957971,
        "EffectiveScore": 0.7501890221271492
    },
    {
        "username": "FP16",
        "userAge": 24,
        "usergender": "female",
        "inputtechnique": "BareHandIntenSelect",
        "radius": 0.21,
        "distance": 0.75,
        "spacing": 0.7,
        "clickDuration": 1.6878888813,
        "isCorrect": 0.6,
        "HeisenbergError": 0.3,
        "HeisenbergAngle": 0.6286362827944592,
        "EffectiveScore": 0.35547363730359094
    },
    {
        "username": "FP16",
        "userAge": 24,
        "usergender": "female",
        "inputtechnique": "BareHandIntenSelect",
        "radius": 0.21,
        "distance": 0.75,
        "spacing": 0.3,
        "clickDuration": 2.80863747,
        "isCorrect": 0.6666666666666666,
        "HeisenbergError": 0.2222222222222222,
        "HeisenbergAngle": 1.11962095896701,
        "EffectiveScore": 0.2373630181137855
    },
    {
        "username": "FP16",
        "userAge": 24,
        "usergender": "female",
        "inputtechnique": "BareHandIntenSelect",
        "radius": 0.21,
        "distance": 0.75,
        "spacing": 0.5,
        "clickDuration": 1.5082954464166667,
        "isCorrect": 0.5,
        "HeisenbergError": 0.16666666666666666,
        "HeisenbergAngle": 0.5287116463490215,
        "EffectiveScore": 0.3315000394570408
    },
    {
        "username": "FP16",
        "userAge": 24,
        "usergender": "female",
        "inputtechnique": "BareHandIntenSelect",
        "radius": 0.21,
        "distance": 0.75,
        "spacing": 0.7,
        "clickDuration": 1.0380808445714285,
        "isCorrect": 0.8571428571428571,
        "HeisenbergError": 0.0,
        "HeisenbergAngle": 0.9064672932726058,
        "EffectiveScore": 0.8256995219835006
    },
    {
        "username": "FP16",
        "userAge": 24,
        "usergender": "female",
        "inputtechnique": "BareHandIntenSelect",
        "radius": 0.21,
        "distance": 0.75,
        "spacing": 0.3,
        "clickDuration": 2.399476289375,
        "isCorrect": 0.75,
        "HeisenbergError": 0.125,
        "HeisenbergAngle": 0.50343062910624,
        "EffectiveScore": 0.31256820637113075
    },
    {
        "username": "FP16",
        "userAge": 24,
        "usergender": "female",
        "inputtechnique": "BareHandIntenSelect",
        "radius": 0.21,
        "distance": 0.75,
        "spacing": 0.5,
        "clickDuration": 2.468781641125,
        "isCorrect": 0.75,
        "HeisenbergError": 0.0,
        "HeisenbergAngle": 0.8326620374322922,
        "EffectiveScore": 0.30379357473601115
    },
    {
        "username": "FP16",
        "userAge": 24,
        "usergender": "female",
        "inputtechnique": "BareHandIntenSelect",
        "radius": 0.21,
        "distance": 0.75,
        "spacing": 0.7,
        "clickDuration": 1.478166768142857,
        "isCorrect": 0.8571428571428571,
        "HeisenbergError": 0.14285714285714285,
        "HeisenbergAngle": 0.8133822098685407,
        "EffectiveScore": 0.5798688453940528
    },
    {
        "username": "FP16",
        "userAge": 24,
        "usergender": "female",
        "inputtechnique": "BareHandIntenSelect",
        "radius": 0.21,
        "distance": 0.75,
        "spacing": 0.5,
        "clickDuration": 1.733347534,
        "isCorrect": 0.6666666666666666,
        "HeisenbergError": 0.3333333333333333,
        "HeisenbergAngle": 0.6893298723378789,
        "EffectiveScore": 0.38461223360569685
    },
    {
        "username": "FP16",
        "userAge": 24,
        "usergender": "female",
        "inputtechnique": "BareHandIntenSelect",
        "radius": 0.21,
        "distance": 0.75,
        "spacing": 0.3,
        "clickDuration": 1.3857658023571429,
        "isCorrect": 0.42857142857142855,
        "HeisenbergError": 0.35714285714285715,
        "HeisenbergAngle": 0.806427098751004,
        "EffectiveScore": 0.30926685291442635
    },
    {
        "username": "FP17",
        "userAge": 21,
        "usergender": "female",
        "inputtechnique": "BareHandIntenSelect",
        "radius": 0.21,
        "distance": 0.75,
        "spacing": 0.7,
        "clickDuration": 1.7497530533333334,
        "isCorrect": 0.6666666666666666,
        "HeisenbergError": 0.3333333333333333,
        "HeisenbergAngle": 0.8814731112480965,
        "EffectiveScore": 0.38100614563674917
    },
    {
        "username": "FP17",
        "userAge": 21,
        "usergender": "female",
        "inputtechnique": "BareHandIntenSelect",
        "radius": 0.21,
        "distance": 0.75,
        "spacing": 0.3,
        "clickDuration": 2.0930570298888886,
        "isCorrect": 0.6666666666666666,
        "HeisenbergError": 0.1111111111111111,
        "HeisenbergAngle": 0.6581723374734266,
        "EffectiveScore": 0.31851337882659464
    },
    {
        "username": "FP17",
        "userAge": 21,
        "usergender": "female",
        "inputtechnique": "BareHandIntenSelect",
        "radius": 0.21,
        "distance": 0.75,
        "spacing": 0.5,
        "clickDuration": 1.4726653733333335,
        "isCorrect": 0.6666666666666666,
        "HeisenbergError": 0.2222222222222222,
        "HeisenbergAngle": 0.962124889917846,
        "EffectiveScore": 0.4526939240498925
    },
    {
        "username": "FP17",
        "userAge": 21,
        "usergender": "female",
        "inputtechnique": "BareHandIntenSelect",
        "radius": 0.21,
        "distance": 0.75,
        "spacing": 0.3,
        "clickDuration": 1.6302124712727275,
        "isCorrect": 0.5454545454545454,
        "HeisenbergError": 0.36363636363636365,
        "HeisenbergAngle": 0.4476241806705712,
        "EffectiveScore": 0.33459107635748986
    },
    {
        "username": "FP17",
        "userAge": 21,
        "usergender": "female",
        "inputtechnique": "BareHandIntenSelect",
        "radius": 0.21,
        "distance": 0.75,
        "spacing": 0.7,
        "clickDuration": 1.6687075537499998,
        "isCorrect": 0.75,
        "HeisenbergError": 0.25,
        "HeisenbergAngle": 1.0303120435837025,
        "EffectiveScore": 0.4494496344278924
    },
    {
        "username": "FP17",
        "userAge": 21,
        "usergender": "female",
        "inputtechnique": "BareHandIntenSelect",
        "radius": 0.21,
        "distance": 0.75,
        "spacing": 0.5,
        "clickDuration": 1.9510247528571427,
        "isCorrect": 0.8571428571428571,
        "HeisenbergError": 0.14285714285714285,
        "HeisenbergAngle": 0.8201718656593432,
        "EffectiveScore": 0.4393295655975814
    },
    {
        "username": "FP17",
        "userAge": 21,
        "usergender": "female",
        "inputtechnique": "BareHandIntenSelect",
        "radius": 0.21,
        "distance": 0.75,
        "spacing": 0.7,
        "clickDuration": 1.202060501,
        "isCorrect": 1.0,
        "HeisenbergError": 0.0,
        "HeisenbergAngle": 0.6010463675220443,
        "EffectiveScore": 0.8319048826311946
    },
    {
        "username": "FP17",
        "userAge": 21,
        "usergender": "female",
        "inputtechnique": "BareHandIntenSelect",
        "radius": 0.21,
        "distance": 0.75,
        "spacing": 0.3,
        "clickDuration": 2.718632385,
        "isCorrect": 1.0,
        "HeisenbergError": 0.0,
        "HeisenbergAngle": 0.33311993589947403,
        "EffectiveScore": 0.36783200462022014
    },
    {
        "username": "FP17",
        "userAge": 21,
        "usergender": "female",
        "inputtechnique": "BareHandIntenSelect",
        "radius": 0.21,
        "distance": 0.75,
        "spacing": 0.5,
        "clickDuration": 1.8830021383333335,
        "isCorrect": 1.0,
        "HeisenbergError": 0.0,
        "HeisenbergAngle": 0.40024324221190116,
        "EffectiveScore": 0.531066842486494
    },
    {
        "username": "FP18",
        "userAge": 28,
        "usergender": "male",
        "inputtechnique": "BareHandIntenSelect",
        "radius": 0.21,
        "distance": 0.75,
        "spacing": 0.3,
        "clickDuration": 2.06862404,
        "isCorrect": 0.6666666666666666,
        "HeisenbergError": 0.1111111111111111,
        "HeisenbergAngle": 0.8225578042928078,
        "EffectiveScore": 0.3222754129197235
    },
    {
        "username": "FP18",
        "userAge": 28,
        "usergender": "male",
        "inputtechnique": "BareHandIntenSelect",
        "radius": 0.21,
        "distance": 0.75,
        "spacing": 0.7,
        "clickDuration": 1.5759877437499998,
        "isCorrect": 0.75,
        "HeisenbergError": 0.25,
        "HeisenbergAngle": 1.5532174104037892,
        "EffectiveScore": 0.47589202579418866
    },
    {
        "username": "FP18",
        "userAge": 28,
        "usergender": "male",
        "inputtechnique": "BareHandIntenSelect",
        "radius": 0.21,
        "distance": 0.75,
        "spacing": 0.5,
        "clickDuration": 1.45502135,
        "isCorrect": 0.6,
        "HeisenbergError": 0.3,
        "HeisenbergAngle": 0.8957519858831079,
        "EffectiveScore": 0.4123650831652745
    },
    {
        "username": "FP18",
        "userAge": 28,
        "usergender": "male",
        "inputtechnique": "BareHandIntenSelect",
        "radius": 0.21,
        "distance": 0.75,
        "spacing": 0.7,
        "clickDuration": 1.1322351003333335,
        "isCorrect": 1.0,
        "HeisenbergError": 0.0,
        "HeisenbergAngle": 1.2102764969507938,
        "EffectiveScore": 0.8832087962169667
    },
    {
        "username": "FP18",
        "userAge": 28,
        "usergender": "male",
        "inputtechnique": "BareHandIntenSelect",
        "radius": 0.21,
        "distance": 0.75,
        "spacing": 0.3,
        "clickDuration": 1.7916367260000001,
        "isCorrect": 0.75,
        "HeisenbergError": 0.125,
        "HeisenbergAngle": 0.5798494775534202,
        "EffectiveScore": 0.41861164661122263
    },
    {
        "username": "FP18",
        "userAge": 28,
        "usergender": "male",
        "inputtechnique": "BareHandIntenSelect",
        "radius": 0.21,
        "distance": 0.75,
        "spacing": 0.5,
        "clickDuration": 2.19347030025,
        "isCorrect": 0.75,
        "HeisenbergError": 0.125,
        "HeisenbergAngle": 0.7138355269310575,
        "EffectiveScore": 0.3419239366562287
    },
    {
        "username": "FP18",
        "userAge": 28,
        "usergender": "male",
        "inputtechnique": "BareHandIntenSelect",
        "radius": 0.21,
        "distance": 0.75,
        "spacing": 0.5,
        "clickDuration": 1.4584107335454546,
        "isCorrect": 0.5454545454545454,
        "HeisenbergError": 0.36363636363636365,
        "HeisenbergAngle": 1.6099766398345239,
        "EffectiveScore": 0.3740061238636963
    },
    {
        "username": "FP18",
        "userAge": 28,
        "usergender": "male",
        "inputtechnique": "BareHandIntenSelect",
        "radius": 0.21,
        "distance": 0.75,
        "spacing": 0.7,
        "clickDuration": 1.43730004125,
        "isCorrect": 0.75,
        "HeisenbergError": 0.25,
        "HeisenbergAngle": 1.403427285437918,
        "EffectiveScore": 0.5218117153518866
    },
    {
        "username": "FP18",
        "userAge": 28,
        "usergender": "male",
        "inputtechnique": "BareHandIntenSelect",
        "radius": 0.21,
        "distance": 0.75,
        "spacing": 0.3,
        "clickDuration": 1.6791874482499998,
        "isCorrect": 0.5,
        "HeisenbergError": 0.3333333333333333,
        "HeisenbergAngle": 1.0675494542415087,
        "EffectiveScore": 0.29776306422554877
    },
    {
        "username": "FP19",
        "userAge": 23,
        "usergender": "female",
        "inputtechnique": "BareHandIntenSelect",
        "radius": 0.21,
        "distance": 0.75,
        "spacing": 0.3,
        "clickDuration": 1.9185249275,
        "isCorrect": 0.75,
        "HeisenbergError": 0.125,
        "HeisenbergAngle": 0.5247692994137277,
        "EffectiveScore": 0.390925335005844
    },
    {
        "username": "FP19",
        "userAge": 23,
        "usergender": "female",
        "inputtechnique": "BareHandIntenSelect",
        "radius": 0.21,
        "distance": 0.75,
        "spacing": 0.7,
        "clickDuration": 1.1747957323333331,
        "isCorrect": 0.6666666666666666,
        "HeisenbergError": 0.3333333333333333,
        "HeisenbergAngle": 1.0459513931492397,
        "EffectiveScore": 0.5674745390354453
    },
    {
        "username": "FP19",
        "userAge": 23,
        "usergender": "female",
        "inputtechnique": "BareHandIntenSelect",
        "radius": 0.21,
        "distance": 0.75,
        "spacing": 0.5,
        "clickDuration": 1.2326967377142861,
        "isCorrect": 0.8571428571428571,
        "HeisenbergError": 0.0,
        "HeisenbergAngle": 0.6044316191770571,
        "EffectiveScore": 0.6953396005023949
    },
    {
        "username": "FP19",
        "userAge": 23,
        "usergender": "female",
        "inputtechnique": "BareHandIntenSelect",
        "radius": 0.21,
        "distance": 0.75,
        "spacing": 0.5,
        "clickDuration": 1.3808890249,
        "isCorrect": 0.6,
        "HeisenbergError": 0.1,
        "HeisenbergAngle": 0.9657697652573873,
        "EffectiveScore": 0.43450269296147837
    },
    {
        "username": "FP19",
        "userAge": 23,
        "usergender": "female",
        "inputtechnique": "BareHandIntenSelect",
        "radius": 0.21,
        "distance": 0.75,
        "spacing": 0.7,
        "clickDuration": 1.4933973342000002,
        "isCorrect": 0.6,
        "HeisenbergError": 0.2,
        "HeisenbergAngle": 0.8279719185502572,
        "EffectiveScore": 0.40176849540274207
    },
    {
        "username": "FP19",
        "userAge": 23,
        "usergender": "female",
        "inputtechnique": "BareHandIntenSelect",
        "radius": 0.21,
        "distance": 0.75,
        "spacing": 0.3,
        "clickDuration": 1.6944919837499999,
        "isCorrect": 0.75,
        "HeisenbergError": 0.0,
        "HeisenbergAngle": 0.5296705355615221,
        "EffectiveScore": 0.44261053294581576
    },
    {
        "username": "FP19",
        "userAge": 23,
        "usergender": "female",
        "inputtechnique": "BareHandIntenSelect",
        "radius": 0.21,
        "distance": 0.75,
        "spacing": 0.7,
        "clickDuration": 1.622093082857143,
        "isCorrect": 0.8571428571428571,
        "HeisenbergError": 0.14285714285714285,
        "HeisenbergAngle": 1.2934145315595396,
        "EffectiveScore": 0.528417799324495
    },
    {
        "username": "FP19",
        "userAge": 23,
        "usergender": "female",
        "inputtechnique": "BareHandIntenSelect",
        "radius": 0.21,
        "distance": 0.75,
        "spacing": 0.5,
        "clickDuration": 1.22701658625,
        "isCorrect": 0.75,
        "HeisenbergError": 0.0,
        "HeisenbergAngle": 0.6414366821982668,
        "EffectiveScore": 0.6112386812081694
    },
    {
        "username": "FP19",
        "userAge": 23,
        "usergender": "female",
        "inputtechnique": "BareHandIntenSelect",
        "radius": 0.21,
        "distance": 0.75,
        "spacing": 0.3,
        "clickDuration": 1.7064191471428571,
        "isCorrect": 0.8571428571428571,
        "HeisenbergError": 0.14285714285714285,
        "HeisenbergAngle": 0.17471552418523695,
        "EffectiveScore": 0.5023049926379544
    },
    {
        "username": "FP2",
        "userAge": 27,
        "usergender": "male",
        "inputtechnique": "BareHandIntenSelect",
        "radius": 0.21,
        "distance": 0.75,
        "spacing": 0.7,
        "clickDuration": 1.64253535375,
        "isCorrect": 1.0,
        "HeisenbergError": 0.0,
        "HeisenbergAngle": 1.164802512285437,
        "EffectiveScore": 0.6088149017413501
    },
    {
        "username": "FP2",
        "userAge": 27,
        "usergender": "male",
        "inputtechnique": "BareHandIntenSelect",
        "radius": 0.21,
        "distance": 0.75,
        "spacing": 0.3,
        "clickDuration": 2.228238128,
        "isCorrect": 0.8,
        "HeisenbergError": 0.2,
        "HeisenbergAngle": 0.32405733666626724,
        "EffectiveScore": 0.35902805447371827
    },
    {
        "username": "FP2",
        "userAge": 27,
        "usergender": "male",
        "inputtechnique": "BareHandIntenSelect",
        "radius": 0.21,
        "distance": 0.75,
        "spacing": 0.5,
        "clickDuration": 1.593694277,
        "isCorrect": 0.8,
        "HeisenbergError": 0.2,
        "HeisenbergAngle": 0.5544584045733164,
        "EffectiveScore": 0.5019783352086419
    },
    {
        "username": "FP2",
        "userAge": 27,
        "usergender": "male",
        "inputtechnique": "BareHandIntenSelect",
        "radius": 0.21,
        "distance": 0.75,
        "spacing": 0.3,
        "clickDuration": 2.597090637777778,
        "isCorrect": 0.8888888888888888,
        "HeisenbergError": 0.0,
        "HeisenbergAngle": 0.3502553493656172,
        "EffectiveScore": 0.3422633295730772
    },
    {
        "username": "FP2",
        "userAge": 27,
        "usergender": "male",
        "inputtechnique": "BareHandIntenSelect",
        "radius": 0.21,
        "distance": 0.75,
        "spacing": 0.7,
        "clickDuration": 2.469542825,
        "isCorrect": 1.0,
        "HeisenbergError": 0.0,
        "HeisenbergAngle": 0.8422894423555136,
        "EffectiveScore": 0.40493324913286327
    },
    {
        "username": "FP2",
        "userAge": 27,
        "usergender": "male",
        "inputtechnique": "BareHandIntenSelect",
        "radius": 0.21,
        "distance": 0.75,
        "spacing": 0.5,
        "clickDuration": 1.5747471655555556,
        "isCorrect": 0.8888888888888888,
        "HeisenbergError": 0.1111111111111111,
        "HeisenbergAngle": 0.6992881516431069,
        "EffectiveScore": 0.5644645110856875
    },
    {
        "username": "FP2",
        "userAge": 27,
        "usergender": "male",
        "inputtechnique": "BareHandIntenSelect",
        "radius": 0.21,
        "distance": 0.75,
        "spacing": 0.5,
        "clickDuration": 2.0360319377777776,
        "isCorrect": 0.8888888888888888,
        "HeisenbergError": 0.1111111111111111,
        "HeisenbergAngle": 0.42090806554135507,
        "EffectiveScore": 0.43657904986454416
    },
    {
        "username": "FP2",
        "userAge": 27,
        "usergender": "male",
        "inputtechnique": "BareHandIntenSelect",
        "radius": 0.21,
        "distance": 0.75,
        "spacing": 0.3,
        "clickDuration": 2.317840203333333,
        "isCorrect": 0.8888888888888888,
        "HeisenbergError": 0.0,
        "HeisenbergAngle": 0.1719518334029407,
        "EffectiveScore": 0.38349877942860755
    },
    {
        "username": "FP2",
        "userAge": 27,
        "usergender": "male",
        "inputtechnique": "BareHandIntenSelect",
        "radius": 0.21,
        "distance": 0.75,
        "spacing": 0.7,
        "clickDuration": 1.4387144035454544,
        "isCorrect": 0.7272727272727273,
        "HeisenbergError": 0.18181818181818182,
        "HeisenbergAngle": 0.7695887441449866,
        "EffectiveScore": 0.5055018045836572
    },
    {
        "username": "FP20",
        "userAge": 23,
        "usergender": "female",
        "inputtechnique": "BareHandIntenSelect",
        "radius": 0.21,
        "distance": 0.75,
        "spacing": 0.7,
        "clickDuration": 2.5371522843333336,
        "isCorrect": 0.6666666666666666,
        "HeisenbergError": 0.2222222222222222,
        "HeisenbergAngle": 0.4588828921930439,
        "EffectiveScore": 0.26276178642617076
    },
    {
        "username": "FP20",
        "userAge": 23,
        "usergender": "female",
        "inputtechnique": "BareHandIntenSelect",
        "radius": 0.21,
        "distance": 0.75,
        "spacing": 0.5,
        "clickDuration": 3.063049231666666,
        "isCorrect": 1.0,
        "HeisenbergError": 0.0,
        "HeisenbergAngle": 0.4046955382699868,
        "EffectiveScore": 0.3264720624342953
    },
    {
        "username": "FP20",
        "userAge": 23,
        "usergender": "female",
        "inputtechnique": "BareHandIntenSelect",
        "radius": 0.21,
        "distance": 0.75,
        "spacing": 0.3,
        "clickDuration": 2.3024719866666667,
        "isCorrect": 1.0,
        "HeisenbergError": 0.0,
        "HeisenbergAngle": 0.06480238092754562,
        "EffectiveScore": 0.43431581612756964
    },
    {
        "username": "FP20",
        "userAge": 23,
        "usergender": "female",
        "inputtechnique": "BareHandIntenSelect",
        "radius": 0.21,
        "distance": 0.75,
        "spacing": 0.3,
        "clickDuration": 5.63839107142857,
        "isCorrect": 0.8571428571428571,
        "HeisenbergError": 0.14285714285714285,
        "HeisenbergAngle": 0.6766999138025814,
        "EffectiveScore": 0.1520190505206811
    },
    {
        "username": "FP20",
        "userAge": 23,
        "usergender": "female",
        "inputtechnique": "BareHandIntenSelect",
        "radius": 0.21,
        "distance": 0.75,
        "spacing": 0.5,
        "clickDuration": 1.3934060883333332,
        "isCorrect": 1.0,
        "HeisenbergError": 0.0,
        "HeisenbergAngle": 0.1700251336533006,
        "EffectiveScore": 0.7176658752769696
    },
    {
        "username": "FP20",
        "userAge": 23,
        "usergender": "female",
        "inputtechnique": "BareHandIntenSelect",
        "radius": 0.21,
        "distance": 0.75,
        "spacing": 0.7,
        "clickDuration": 1.9590323183333334,
        "isCorrect": 1.0,
        "HeisenbergError": 0.0,
        "HeisenbergAngle": 0.35615183532699524,
        "EffectiveScore": 0.5104561015362729
    },
    {
        "username": "FP20",
        "userAge": 23,
        "usergender": "female",
        "inputtechnique": "BareHandIntenSelect",
        "radius": 0.21,
        "distance": 0.75,
        "spacing": 0.3,
        "clickDuration": 4.36836962,
        "isCorrect": 0.6666666666666666,
        "HeisenbergError": 0.3333333333333333,
        "HeisenbergAngle": 0.5413646908357401,
        "EffectiveScore": 0.1526122385831139
    },
    {
        "username": "FP20",
        "userAge": 23,
        "usergender": "female",
        "inputtechnique": "BareHandIntenSelect",
        "radius": 0.21,
        "distance": 0.75,
        "spacing": 0.5,
        "clickDuration": 1.4674894285714284,
        "isCorrect": 0.8571428571428571,
        "HeisenbergError": 0.0,
        "HeisenbergAngle": 0.12579941907579872,
        "EffectiveScore": 0.5840879262600676
    },
    {
        "username": "FP20",
        "userAge": 23,
        "usergender": "female",
        "inputtechnique": "BareHandIntenSelect",
        "radius": 0.21,
        "distance": 0.75,
        "spacing": 0.7,
        "clickDuration": 1.7109720954285714,
        "isCorrect": 0.8571428571428571,
        "HeisenbergError": 0.0,
        "HeisenbergAngle": 0.2973761475060898,
        "EffectiveScore": 0.5009683439215625
    },
    {
        "username": "FP21",
        "userAge": 20,
        "usergender": "female",
        "inputtechnique": "BareHandIntenSelect",
        "radius": 0.21,
        "distance": 0.75,
        "spacing": 0.3,
        "clickDuration": 1.7874314616666667,
        "isCorrect": 1.0,
        "HeisenbergError": 0.0,
        "HeisenbergAngle": 0.3662725131901319,
        "EffectiveScore": 0.5594620109615634
    },
    {
        "username": "FP21",
        "userAge": 20,
        "usergender": "female",
        "inputtechnique": "BareHandIntenSelect",
        "radius": 0.21,
        "distance": 0.75,
        "spacing": 0.7,
        "clickDuration": 1.2451814861666668,
        "isCorrect": 1.0,
        "HeisenbergError": 0.0,
        "HeisenbergAngle": 0.47528622229205336,
        "EffectiveScore": 0.8030957825100128
    },
    {
        "username": "FP21",
        "userAge": 20,
        "usergender": "female",
        "inputtechnique": "BareHandIntenSelect",
        "radius": 0.21,
        "distance": 0.75,
        "spacing": 0.5,
        "clickDuration": 1.2185164711666667,
        "isCorrect": 1.0,
        "HeisenbergError": 0.0,
        "HeisenbergAngle": 0.28979166991667565,
        "EffectiveScore": 0.8206700718969777
    },
    {
        "username": "FP21",
        "userAge": 20,
        "usergender": "female",
        "inputtechnique": "BareHandIntenSelect",
        "radius": 0.21,
        "distance": 0.75,
        "spacing": 0.3,
        "clickDuration": 1.9702459914285717,
        "isCorrect": 0.8571428571428571,
        "HeisenbergError": 0.14285714285714285,
        "HeisenbergAngle": 0.28589657988800177,
        "EffectiveScore": 0.43504357368156155
    },
    {
        "username": "FP21",
        "userAge": 20,
        "usergender": "female",
        "inputtechnique": "BareHandIntenSelect",
        "radius": 0.21,
        "distance": 0.75,
        "spacing": 0.5,
        "clickDuration": 1.3802623799999998,
        "isCorrect": 1.0,
        "HeisenbergError": 0.0,
        "HeisenbergAngle": 0.29744836444990363,
        "EffectiveScore": 0.7244999316724116
    },
    {
        "username": "FP21",
        "userAge": 20,
        "usergender": "female",
        "inputtechnique": "BareHandIntenSelect",
        "radius": 0.21,
        "distance": 0.75,
        "spacing": 0.7,
        "clickDuration": 2.203826925,
        "isCorrect": 1.0,
        "HeisenbergError": 0.0,
        "HeisenbergAngle": 0.486627670718879,
        "EffectiveScore": 0.45375614058259134
    },
    {
        "username": "FP21",
        "userAge": 20,
        "usergender": "female",
        "inputtechnique": "BareHandIntenSelect",
        "radius": 0.21,
        "distance": 0.75,
        "spacing": 0.5,
        "clickDuration": 1.410266013,
        "isCorrect": 0.8571428571428571,
        "HeisenbergError": 0.14285714285714285,
        "HeisenbergAngle": 0.4996622453827841,
        "EffectiveScore": 0.607788069230636
    },
    {
        "username": "FP21",
        "userAge": 20,
        "usergender": "female",
        "inputtechnique": "BareHandIntenSelect",
        "radius": 0.21,
        "distance": 0.75,
        "spacing": 0.3,
        "clickDuration": 2.7859791116666663,
        "isCorrect": 1.0,
        "HeisenbergError": 0.0,
        "HeisenbergAngle": 0.21455470613493563,
        "EffectiveScore": 0.35894023606004943
    },
    {
        "username": "FP21",
        "userAge": 20,
        "usergender": "female",
        "inputtechnique": "BareHandIntenSelect",
        "radius": 0.21,
        "distance": 0.75,
        "spacing": 0.7,
        "clickDuration": 2.087322412857143,
        "isCorrect": 0.8571428571428571,
        "HeisenbergError": 0.14285714285714285,
        "HeisenbergAngle": 0.34966621238876855,
        "EffectiveScore": 0.41064229074682973
    },
    {
        "username": "FP22",
        "userAge": 21,
        "usergender": "male",
        "inputtechnique": "BareHandIntenSelect",
        "radius": 0.21,
        "distance": 0.75,
        "spacing": 0.7,
        "clickDuration": 1.49207966,
        "isCorrect": 0.8571428571428571,
        "HeisenbergError": 0.0,
        "HeisenbergAngle": 0.9139132168563658,
        "EffectiveScore": 0.5744618602621103
    },
    {
        "username": "FP22",
        "userAge": 21,
        "usergender": "male",
        "inputtechnique": "BareHandIntenSelect",
        "radius": 0.21,
        "distance": 0.75,
        "spacing": 0.5,
        "clickDuration": 1.583248706888889,
        "isCorrect": 0.6666666666666666,
        "HeisenbergError": 0.2222222222222222,
        "HeisenbergAngle": 0.6675712479914144,
        "EffectiveScore": 0.42107513732108337
    },
    {
        "username": "FP22",
        "userAge": 21,
        "usergender": "male",
        "inputtechnique": "BareHandIntenSelect",
        "radius": 0.21,
        "distance": 0.75,
        "spacing": 0.3,
        "clickDuration": 1.7371584350000002,
        "isCorrect": 1.0,
        "HeisenbergError": 0.0,
        "HeisenbergAngle": 0.649143183752965,
        "EffectiveScore": 0.5756527325614949
    },
    {
        "username": "FP22",
        "userAge": 21,
        "usergender": "male",
        "inputtechnique": "BareHandIntenSelect",
        "radius": 0.21,
        "distance": 0.75,
        "spacing": 0.5,
        "clickDuration": 1.4469074925,
        "isCorrect": 0.75,
        "HeisenbergError": 0.25,
        "HeisenbergAngle": 0.5625206961040007,
        "EffectiveScore": 0.5183468907912923
    },
    {
        "username": "FP22",
        "userAge": 21,
        "usergender": "male",
        "inputtechnique": "BareHandIntenSelect",
        "radius": 0.21,
        "distance": 0.75,
        "spacing": 0.7,
        "clickDuration": 1.7341095485714286,
        "isCorrect": 0.8571428571428571,
        "HeisenbergError": 0.0,
        "HeisenbergAngle": 0.8245347961194109,
        "EffectiveScore": 0.49428414591741177
    },
    {
        "username": "FP22",
        "userAge": 21,
        "usergender": "male",
        "inputtechnique": "BareHandIntenSelect",
        "radius": 0.21,
        "distance": 0.75,
        "spacing": 0.3,
        "clickDuration": 1.496280956285714,
        "isCorrect": 0.8571428571428571,
        "HeisenbergError": 0.14285714285714285,
        "HeisenbergAngle": 0.5547080131212883,
        "EffectiveScore": 0.5728488714249105
    },
    {
        "username": "FP22",
        "userAge": 21,
        "usergender": "male",
        "inputtechnique": "BareHandIntenSelect",
        "radius": 0.21,
        "distance": 0.75,
        "spacing": 0.5,
        "clickDuration": 1.2860943797777777,
        "isCorrect": 0.6666666666666666,
        "HeisenbergError": 0.1111111111111111,
        "HeisenbergAngle": 1.4805141722676916,
        "EffectiveScore": 0.5183652748578677
    },
    {
        "username": "FP22",
        "userAge": 21,
        "usergender": "male",
        "inputtechnique": "BareHandIntenSelect",
        "radius": 0.21,
        "distance": 0.75,
        "spacing": 0.3,
        "clickDuration": 2.481833975,
        "isCorrect": 1.0,
        "HeisenbergError": 0.0,
        "HeisenbergAngle": 0.3250738719541635,
        "EffectiveScore": 0.40292783887769934
    },
    {
        "username": "FP22",
        "userAge": 21,
        "usergender": "male",
        "inputtechnique": "BareHandIntenSelect",
        "radius": 0.21,
        "distance": 0.75,
        "spacing": 0.7,
        "clickDuration": 1.2136453683333335,
        "isCorrect": 1.0,
        "HeisenbergError": 0.0,
        "HeisenbergAngle": 1.0111715568899486,
        "EffectiveScore": 0.8239639239700417
    },
    {
        "username": "FP23",
        "userAge": 29,
        "usergender": "male",
        "inputtechnique": "BareHandIntenSelect",
        "radius": 0.21,
        "distance": 0.75,
        "spacing": 0.3,
        "clickDuration": 0.9249208756153847,
        "isCorrect": 0.46153846153846156,
        "HeisenbergError": 0.3076923076923077,
        "HeisenbergAngle": 0.6272972933148567,
        "EffectiveScore": 0.499003183630581
    },
    {
        "username": "FP23",
        "userAge": 29,
        "usergender": "male",
        "inputtechnique": "BareHandIntenSelect",
        "radius": 0.21,
        "distance": 0.75,
        "spacing": 0.7,
        "clickDuration": 0.9423990800000001,
        "isCorrect": 0.8571428571428571,
        "HeisenbergError": 0.14285714285714285,
        "HeisenbergAngle": 1.3334828468022903,
        "EffectiveScore": 0.9095327821657646
    },
    {
        "username": "FP23",
        "userAge": 29,
        "usergender": "male",
        "inputtechnique": "BareHandIntenSelect",
        "radius": 0.21,
        "distance": 0.75,
        "spacing": 0.5,
        "clickDuration": 0.8750696852727272,
        "isCorrect": 0.5454545454545454,
        "HeisenbergError": 0.2727272727272727,
        "HeisenbergAngle": 1.2369517348362726,
        "EffectiveScore": 0.6233269814215392
    },
    {
        "username": "FP23",
        "userAge": 29,
        "usergender": "male",
        "inputtechnique": "BareHandIntenSelect",
        "radius": 0.21,
        "distance": 0.75,
        "spacing": 0.3,
        "clickDuration": 1.3273763444545457,
        "isCorrect": 0.5454545454545454,
        "HeisenbergError": 0.18181818181818182,
        "HeisenbergAngle": 0.5975396761566145,
        "EffectiveScore": 0.4109268239812479
    },
    {
        "username": "FP23",
        "userAge": 29,
        "usergender": "male",
        "inputtechnique": "BareHandIntenSelect",
        "radius": 0.21,
        "distance": 0.75,
        "spacing": 0.7,
        "clickDuration": 1.0469554856666667,
        "isCorrect": 1.0,
        "HeisenbergError": 0.0,
        "HeisenbergAngle": 2.019589817725169,
        "EffectiveScore": 0.9551504468819254
    },
    {
        "username": "FP23",
        "userAge": 29,
        "usergender": "male",
        "inputtechnique": "BareHandIntenSelect",
        "radius": 0.21,
        "distance": 0.75,
        "spacing": 0.5,
        "clickDuration": 1.0261543228571428,
        "isCorrect": 0.8571428571428571,
        "HeisenbergError": 0.14285714285714285,
        "HeisenbergAngle": 0.9557497827750063,
        "EffectiveScore": 0.8352962493558439
    },
    {
        "username": "FP23",
        "userAge": 29,
        "usergender": "male",
        "inputtechnique": "BareHandIntenSelect",
        "radius": 0.21,
        "distance": 0.75,
        "spacing": 0.3,
        "clickDuration": 0.9948571873750001,
        "isCorrect": 0.75,
        "HeisenbergError": 0.125,
        "HeisenbergAngle": 0.6066979499366812,
        "EffectiveScore": 0.7538770484022206
    },
    {
        "username": "FP23",
        "userAge": 29,
        "usergender": "male",
        "inputtechnique": "BareHandIntenSelect",
        "radius": 0.21,
        "distance": 0.75,
        "spacing": 0.7,
        "clickDuration": 1.0418109705,
        "isCorrect": 0.75,
        "HeisenbergError": 0.0,
        "HeisenbergAngle": 0.857398787131282,
        "EffectiveScore": 0.719900271006025
    },
    {
        "username": "FP23",
        "userAge": 29,
        "usergender": "male",
        "inputtechnique": "BareHandIntenSelect",
        "radius": 0.21,
        "distance": 0.75,
        "spacing": 0.5,
        "clickDuration": 1.5061722988571427,
        "isCorrect": 0.8571428571428571,
        "HeisenbergError": 0.14285714285714285,
        "HeisenbergAngle": 1.53214040913247,
        "EffectiveScore": 0.5690868553307229
    },
    {
        "username": "FP3",
        "userAge": 23,
        "usergender": "female",
        "inputtechnique": "BareHandIntenSelect",
        "radius": 0.21,
        "distance": 0.75,
        "spacing": 0.5,
        "clickDuration": 2.0964616088571426,
        "isCorrect": 0.8571428571428571,
        "HeisenbergError": 0.0,
        "HeisenbergAngle": 0.8136522569255276,
        "EffectiveScore": 0.4088521600021652
    },
    {
        "username": "FP3",
        "userAge": 23,
        "usergender": "female",
        "inputtechnique": "BareHandIntenSelect",
        "radius": 0.21,
        "distance": 0.75,
        "spacing": 0.3,
        "clickDuration": 1.8681106669999998,
        "isCorrect": 0.6,
        "HeisenbergError": 0.4,
        "HeisenbergAngle": 0.8554979018285472,
        "EffectiveScore": 0.3211801156103564
    },
    {
        "username": "FP3",
        "userAge": 23,
        "usergender": "female",
        "inputtechnique": "BareHandIntenSelect",
        "radius": 0.21,
        "distance": 0.75,
        "spacing": 0.7,
        "clickDuration": 1.3588703775,
        "isCorrect": 1.0,
        "HeisenbergError": 0.0,
        "HeisenbergAngle": 0.6861066852543,
        "EffectiveScore": 0.7359053641597246
    },
    {
        "username": "FP3",
        "userAge": 23,
        "usergender": "female",
        "inputtechnique": "BareHandIntenSelect",
        "radius": 0.21,
        "distance": 0.75,
        "spacing": 0.5,
        "clickDuration": 1.68105060125,
        "isCorrect": 0.75,
        "HeisenbergError": 0.0,
        "HeisenbergAngle": 0.8409867319471636,
        "EffectiveScore": 0.44614956827731006
    },
    {
        "username": "FP3",
        "userAge": 23,
        "usergender": "female",
        "inputtechnique": "BareHandIntenSelect",
        "radius": 0.21,
        "distance": 0.75,
        "spacing": 0.3,
        "clickDuration": 1.0434567946666666,
        "isCorrect": 0.6666666666666666,
        "HeisenbergError": 0.3333333333333333,
        "HeisenbergAngle": 0.3852994531819787,
        "EffectiveScore": 0.6389020322395178
    },
    {
        "username": "FP3",
        "userAge": 23,
        "usergender": "female",
        "inputtechnique": "BareHandIntenSelect",
        "radius": 0.21,
        "distance": 0.75,
        "spacing": 0.7,
        "clickDuration": 0.9869381367142857,
        "isCorrect": 0.8571428571428571,
        "HeisenbergError": 0.14285714285714285,
        "HeisenbergAngle": 0.8776428966109913,
        "EffectiveScore": 0.8684869144852959
    },
    {
        "username": "FP3",
        "userAge": 23,
        "usergender": "female",
        "inputtechnique": "BareHandIntenSelect",
        "radius": 0.21,
        "distance": 0.75,
        "spacing": 0.5,
        "clickDuration": 1.5421211655555558,
        "isCorrect": 0.6666666666666666,
        "HeisenbergError": 0.3333333333333333,
        "HeisenbergAngle": 0.7323726622058132,
        "EffectiveScore": 0.43230498456098754
    },
    {
        "username": "FP3",
        "userAge": 23,
        "usergender": "female",
        "inputtechnique": "BareHandIntenSelect",
        "radius": 0.21,
        "distance": 0.75,
        "spacing": 0.7,
        "clickDuration": 1.6152601821666668,
        "isCorrect": 1.0,
        "HeisenbergError": 0.0,
        "HeisenbergAngle": 0.7079397053183882,
        "EffectiveScore": 0.6190953080132433
    },
    {
        "username": "FP3",
        "userAge": 23,
        "usergender": "female",
        "inputtechnique": "BareHandIntenSelect",
        "radius": 0.21,
        "distance": 0.75,
        "spacing": 0.3,
        "clickDuration": 1.36626909375,
        "isCorrect": 0.75,
        "HeisenbergError": 0.0,
        "HeisenbergAngle": 0.16311633358827057,
        "EffectiveScore": 0.5489401783520363
    },
    {
        "username": "FP4",
        "userAge": 25,
        "usergender": "female",
        "inputtechnique": "BareHandIntenSelect",
        "radius": 0.21,
        "distance": 0.75,
        "spacing": 0.3,
        "clickDuration": 2.373737259625,
        "isCorrect": 0.75,
        "HeisenbergError": 0.125,
        "HeisenbergAngle": 0.5183049348302827,
        "EffectiveScore": 0.31595746199749336
    },
    {
        "username": "FP4",
        "userAge": 25,
        "usergender": "female",
        "inputtechnique": "BareHandIntenSelect",
        "radius": 0.21,
        "distance": 0.75,
        "spacing": 0.5,
        "clickDuration": 1.2544740181111114,
        "isCorrect": 0.6666666666666666,
        "HeisenbergError": 0.3333333333333333,
        "HeisenbergAngle": 0.6054193922268577,
        "EffectiveScore": 0.5314312269858574
    },
    {
        "username": "FP4",
        "userAge": 25,
        "usergender": "female",
        "inputtechnique": "BareHandIntenSelect",
        "radius": 0.21,
        "distance": 0.75,
        "spacing": 0.7,
        "clickDuration": 1.295848195818182,
        "isCorrect": 0.5454545454545454,
        "HeisenbergError": 0.36363636363636365,
        "HeisenbergAngle": 0.9058020568189181,
        "EffectiveScore": 0.42092472499076355
    },
    {
        "username": "FP4",
        "userAge": 25,
        "usergender": "female",
        "inputtechnique": "BareHandIntenSelect",
        "radius": 0.21,
        "distance": 0.75,
        "spacing": 0.3,
        "clickDuration": 1.3261360385,
        "isCorrect": 0.6,
        "HeisenbergError": 0.1,
        "HeisenbergAngle": 0.30109091590385517,
        "EffectiveScore": 0.4524422703108675
    },
    {
        "username": "FP4",
        "userAge": 25,
        "usergender": "female",
        "inputtechnique": "BareHandIntenSelect",
        "radius": 0.21,
        "distance": 0.75,
        "spacing": 0.7,
        "clickDuration": 1.2421864169999999,
        "isCorrect": 0.8571428571428571,
        "HeisenbergError": 0.14285714285714285,
        "HeisenbergAngle": 0.6648824461307894,
        "EffectiveScore": 0.6900275557777711
    },
    {
        "username": "FP4",
        "userAge": 25,
        "usergender": "female",
        "inputtechnique": "BareHandIntenSelect",
        "radius": 0.21,
        "distance": 0.75,
        "spacing": 0.5,
        "clickDuration": 1.1586885500000002,
        "isCorrect": 0.75,
        "HeisenbergError": 0.125,
        "HeisenbergAngle": 0.9503969479583844,
        "EffectiveScore": 0.6472835172143541
    },
    {
        "username": "FP4",
        "userAge": 25,
        "usergender": "female",
        "inputtechnique": "BareHandIntenSelect",
        "radius": 0.21,
        "distance": 0.75,
        "spacing": 0.3,
        "clickDuration": 1.8323677487142855,
        "isCorrect": 0.8571428571428571,
        "HeisenbergError": 0.14285714285714285,
        "HeisenbergAngle": 0.23370481421036063,
        "EffectiveScore": 0.46777883846967244
    },
    {
        "username": "FP4",
        "userAge": 25,
        "usergender": "female",
        "inputtechnique": "BareHandIntenSelect",
        "radius": 0.21,
        "distance": 0.75,
        "spacing": 0.5,
        "clickDuration": 1.239942243857143,
        "isCorrect": 0.8571428571428571,
        "HeisenbergError": 0.14285714285714285,
        "HeisenbergAngle": 1.1076617828143926,
        "EffectiveScore": 0.6912764375834999
    },
    {
        "username": "FP4",
        "userAge": 25,
        "usergender": "female",
        "inputtechnique": "BareHandIntenSelect",
        "radius": 0.21,
        "distance": 0.75,
        "spacing": 0.7,
        "clickDuration": 1.170382758125,
        "isCorrect": 0.75,
        "HeisenbergError": 0.125,
        "HeisenbergAngle": 1.1793927470047179,
        "EffectiveScore": 0.6408160021098824
    },
    {
        "username": "FP5",
        "userAge": 25,
        "usergender": "female",
        "inputtechnique": "BareHandIntenSelect",
        "radius": 0.21,
        "distance": 0.75,
        "spacing": 0.7,
        "clickDuration": 1.249885677142857,
        "isCorrect": 0.8571428571428571,
        "HeisenbergError": 0.14285714285714285,
        "HeisenbergAngle": 0.7512178787034791,
        "EffectiveScore": 0.6857770057036097
    },
    {
        "username": "FP5",
        "userAge": 25,
        "usergender": "female",
        "inputtechnique": "BareHandIntenSelect",
        "radius": 0.21,
        "distance": 0.75,
        "spacing": 0.3,
        "clickDuration": 1.332545622857143,
        "isCorrect": 0.8571428571428571,
        "HeisenbergError": 0.0,
        "HeisenbergAngle": 0.4032363391335591,
        "EffectiveScore": 0.6432371563421869
    },
    {
        "username": "FP5",
        "userAge": 25,
        "usergender": "female",
        "inputtechnique": "BareHandIntenSelect",
        "radius": 0.21,
        "distance": 0.75,
        "spacing": 0.5,
        "clickDuration": 1.1881751833333334,
        "isCorrect": 1.0,
        "HeisenbergError": 0.0,
        "HeisenbergAngle": 0.522429870398196,
        "EffectiveScore": 0.8416267348679826
    },
    {
        "username": "FP5",
        "userAge": 25,
        "usergender": "female",
        "inputtechnique": "BareHandIntenSelect",
        "radius": 0.21,
        "distance": 0.75,
        "spacing": 0.5,
        "clickDuration": 1.533625830875,
        "isCorrect": 0.75,
        "HeisenbergError": 0.0,
        "HeisenbergAngle": 0.5974520010766126,
        "EffectiveScore": 0.48903714641536294
    },
    {
        "username": "FP5",
        "userAge": 25,
        "usergender": "female",
        "inputtechnique": "BareHandIntenSelect",
        "radius": 0.21,
        "distance": 0.75,
        "spacing": 0.3,
        "clickDuration": 1.292936111375,
        "isCorrect": 0.75,
        "HeisenbergError": 0.0,
        "HeisenbergAngle": 0.26479374503229897,
        "EffectiveScore": 0.5800750658920005
    },
    {
        "username": "FP5",
        "userAge": 25,
        "usergender": "female",
        "inputtechnique": "BareHandIntenSelect",
        "radius": 0.21,
        "distance": 0.75,
        "spacing": 0.7,
        "clickDuration": 1.4742713737142856,
        "isCorrect": 0.8571428571428571,
        "HeisenbergError": 0.0,
        "HeisenbergAngle": 0.9806252888466146,
        "EffectiveScore": 0.581401004201396
    },
    {
        "username": "FP5",
        "userAge": 25,
        "usergender": "female",
        "inputtechnique": "BareHandIntenSelect",
        "radius": 0.21,
        "distance": 0.75,
        "spacing": 0.5,
        "clickDuration": 1.5377929898999998,
        "isCorrect": 0.6,
        "HeisenbergError": 0.3,
        "HeisenbergAngle": 0.7086763229005215,
        "EffectiveScore": 0.39016955073973714
    },
    {
        "username": "FP5",
        "userAge": 25,
        "usergender": "female",
        "inputtechnique": "BareHandIntenSelect",
        "radius": 0.21,
        "distance": 0.75,
        "spacing": 0.7,
        "clickDuration": 1.2512313533333335,
        "isCorrect": 1.0,
        "HeisenbergError": 0.0,
        "HeisenbergAngle": 0.15247106326076246,
        "EffectiveScore": 0.7992127094129775
    },
    {
        "username": "FP5",
        "userAge": 25,
        "usergender": "female",
        "inputtechnique": "BareHandIntenSelect",
        "radius": 0.21,
        "distance": 0.75,
        "spacing": 0.3,
        "clickDuration": 1.8288583262500002,
        "isCorrect": 0.75,
        "HeisenbergError": 0.125,
        "HeisenbergAngle": 0.49112894367994464,
        "EffectiveScore": 0.4100919077410684
    },
    {
        "username": "FP6",
        "userAge": 28,
        "usergender": "male",
        "inputtechnique": "BareHandIntenSelect",
        "radius": 0.21,
        "distance": 0.75,
        "spacing": 0.3,
        "clickDuration": 1.9533143725,
        "isCorrect": 0.75,
        "HeisenbergError": 0.125,
        "HeisenbergAngle": 0.3706678136092103,
        "EffectiveScore": 0.3839627714611515
    },
    {
        "username": "FP6",
        "userAge": 28,
        "usergender": "male",
        "inputtechnique": "BareHandIntenSelect",
        "radius": 0.21,
        "distance": 0.75,
        "spacing": 0.5,
        "clickDuration": 1.0762492095714287,
        "isCorrect": 0.8571428571428571,
        "HeisenbergError": 0.14285714285714285,
        "HeisenbergAngle": 0.31310270636873255,
        "EffectiveScore": 0.7964167123376364
    },
    {
        "username": "FP6",
        "userAge": 28,
        "usergender": "male",
        "inputtechnique": "BareHandIntenSelect",
        "radius": 0.21,
        "distance": 0.75,
        "spacing": 0.7,
        "clickDuration": 1.198197064375,
        "isCorrect": 0.75,
        "HeisenbergError": 0.25,
        "HeisenbergAngle": 0.4390205563941134,
        "EffectiveScore": 0.6259404419349106
    },
    {
        "username": "FP6",
        "userAge": 28,
        "usergender": "male",
        "inputtechnique": "BareHandIntenSelect",
        "radius": 0.21,
        "distance": 0.75,
        "spacing": 0.3,
        "clickDuration": 2.037354717142857,
        "isCorrect": 0.8571428571428571,
        "HeisenbergError": 0.14285714285714285,
        "HeisenbergAngle": 0.38838233437959996,
        "EffectiveScore": 0.4207136096285167
    },
    {
        "username": "FP6",
        "userAge": 28,
        "usergender": "male",
        "inputtechnique": "BareHandIntenSelect",
        "radius": 0.21,
        "distance": 0.75,
        "spacing": 0.5,
        "clickDuration": 1.5268139749999998,
        "isCorrect": 1.0,
        "HeisenbergError": 0.0,
        "HeisenbergAngle": 0.37767359182165244,
        "EffectiveScore": 0.6549586369878493
    },
    {
        "username": "FP6",
        "userAge": 28,
        "usergender": "male",
        "inputtechnique": "BareHandIntenSelect",
        "radius": 0.21,
        "distance": 0.75,
        "spacing": 0.7,
        "clickDuration": 1.3012131756666665,
        "isCorrect": 1.0,
        "HeisenbergError": 0.0,
        "HeisenbergAngle": 0.5380997210512362,
        "EffectiveScore": 0.7685135830934525
    },
    {
        "username": "FP6",
        "userAge": 28,
        "usergender": "male",
        "inputtechnique": "BareHandIntenSelect",
        "radius": 0.21,
        "distance": 0.75,
        "spacing": 0.5,
        "clickDuration": 1.011923389,
        "isCorrect": 0.8571428571428571,
        "HeisenbergError": 0.0,
        "HeisenbergAngle": 0.37569971563345417,
        "EffectiveScore": 0.8470432311974728
    },
    {
        "username": "FP6",
        "userAge": 28,
        "usergender": "male",
        "inputtechnique": "BareHandIntenSelect",
        "radius": 0.21,
        "distance": 0.75,
        "spacing": 0.7,
        "clickDuration": 0.9802780053333332,
        "isCorrect": 1.0,
        "HeisenbergError": 0.0,
        "HeisenbergAngle": 0.17141033383887727,
        "EffectiveScore": 1.0201187770809572
    },
    {
        "username": "FP6",
        "userAge": 28,
        "usergender": "male",
        "inputtechnique": "BareHandIntenSelect",
        "radius": 0.21,
        "distance": 0.75,
        "spacing": 0.3,
        "clickDuration": 1.9679643249999998,
        "isCorrect": 1.0,
        "HeisenbergError": 0.0,
        "HeisenbergAngle": 0.1760709639802676,
        "EffectiveScore": 0.508139292616496
    },
    {
        "username": "FP7",
        "userAge": 31,
        "usergender": "male",
        "inputtechnique": "BareHandIntenSelect",
        "radius": 0.21,
        "distance": 0.75,
        "spacing": 0.7,
        "clickDuration": 2.749017968875,
        "isCorrect": 0.75,
        "HeisenbergError": 0.0,
        "HeisenbergAngle": 0.5455429752004111,
        "EffectiveScore": 0.2728246990349531
    },
    {
        "username": "FP7",
        "userAge": 31,
        "usergender": "male",
        "inputtechnique": "BareHandIntenSelect",
        "radius": 0.21,
        "distance": 0.75,
        "spacing": 0.5,
        "clickDuration": 1.1316688484,
        "isCorrect": 0.4,
        "HeisenbergError": 0.2,
        "HeisenbergAngle": 0.961995165880183,
        "EffectiveScore": 0.3534602905837132
    },
    {
        "username": "FP7",
        "userAge": 31,
        "usergender": "male",
        "inputtechnique": "BareHandIntenSelect",
        "radius": 0.21,
        "distance": 0.75,
        "spacing": 0.3,
        "clickDuration": 1.639519698625,
        "isCorrect": 0.75,
        "HeisenbergError": 0.125,
        "HeisenbergAngle": 0.7717793635995568,
        "EffectiveScore": 0.45745104534516734
    },
    {
        "username": "FP7",
        "userAge": 31,
        "usergender": "male",
        "inputtechnique": "BareHandIntenSelect",
        "radius": 0.21,
        "distance": 0.75,
        "spacing": 0.5,
        "clickDuration": 1.7974582666428571,
        "isCorrect": 0.42857142857142855,
        "HeisenbergError": 0.42857142857142855,
        "HeisenbergAngle": 0.913077843895297,
        "EffectiveScore": 0.23843192163336205
    },
    {
        "username": "FP7",
        "userAge": 31,
        "usergender": "male",
        "inputtechnique": "BareHandIntenSelect",
        "radius": 0.21,
        "distance": 0.75,
        "spacing": 0.3,
        "clickDuration": 2.516914663636364,
        "isCorrect": 0.5454545454545454,
        "HeisenbergError": 0.2727272727272727,
        "HeisenbergAngle": 0.5956414863751861,
        "EffectiveScore": 0.2167155499290901
    },
    {
        "username": "FP7",
        "userAge": 31,
        "usergender": "male",
        "inputtechnique": "BareHandIntenSelect",
        "radius": 0.21,
        "distance": 0.75,
        "spacing": 0.7,
        "clickDuration": 2.2103194025,
        "isCorrect": 0.75,
        "HeisenbergError": 0.0,
        "HeisenbergAngle": 0.9323242413334452,
        "EffectiveScore": 0.33931747563347914
    },
    {
        "username": "FP7",
        "userAge": 31,
        "usergender": "male",
        "inputtechnique": "BareHandIntenSelect",
        "radius": 0.21,
        "distance": 0.75,
        "spacing": 0.5,
        "clickDuration": 1.89805743125,
        "isCorrect": 0.75,
        "HeisenbergError": 0.25,
        "HeisenbergAngle": 0.5657268111644621,
        "EffectiveScore": 0.3951408359156309
    },
    {
        "username": "FP7",
        "userAge": 31,
        "usergender": "male",
        "inputtechnique": "BareHandIntenSelect",
        "radius": 0.21,
        "distance": 0.75,
        "spacing": 0.7,
        "clickDuration": 1.3108460806666666,
        "isCorrect": 1.0,
        "HeisenbergError": 0.0,
        "HeisenbergAngle": 0.9186935323509652,
        "EffectiveScore": 0.7628660715767809
    },
    {
        "username": "FP7",
        "userAge": 31,
        "usergender": "male",
        "inputtechnique": "BareHandIntenSelect",
        "radius": 0.21,
        "distance": 0.75,
        "spacing": 0.3,
        "clickDuration": 3.0471627999999997,
        "isCorrect": 0.5454545454545454,
        "HeisenbergError": 0.2727272727272727,
        "HeisenbergAngle": 0.6350898256770422,
        "EffectiveScore": 0.17900407075544025
    },
    {
        "username": "FP8",
        "userAge": 23,
        "usergender": "male",
        "inputtechnique": "BareHandIntenSelect",
        "radius": 0.21,
        "distance": 0.75,
        "spacing": 0.7,
        "clickDuration": 1.0500257312499999,
        "isCorrect": 0.75,
        "HeisenbergError": 0.125,
        "HeisenbergAngle": 0.7667814982251483,
        "EffectiveScore": 0.7142682104629615
    },
    {
        "username": "FP8",
        "userAge": 23,
        "usergender": "male",
        "inputtechnique": "BareHandIntenSelect",
        "radius": 0.21,
        "distance": 0.75,
        "spacing": 0.5,
        "clickDuration": 1.5815795300000002,
        "isCorrect": 0.8571428571428571,
        "HeisenbergError": 0.0,
        "HeisenbergAngle": 1.487597761348497,
        "EffectiveScore": 0.5419536867316795
    },
    {
        "username": "FP8",
        "userAge": 23,
        "usergender": "male",
        "inputtechnique": "BareHandIntenSelect",
        "radius": 0.21,
        "distance": 0.75,
        "spacing": 0.3,
        "clickDuration": 1.3764542684444443,
        "isCorrect": 0.6666666666666666,
        "HeisenbergError": 0.3333333333333333,
        "HeisenbergAngle": 0.6418706671685109,
        "EffectiveScore": 0.4843362267458973
    },
    {
        "username": "FP8",
        "userAge": 23,
        "usergender": "male",
        "inputtechnique": "BareHandIntenSelect",
        "radius": 0.21,
        "distance": 0.75,
        "spacing": 0.5,
        "clickDuration": 1.1402841045555554,
        "isCorrect": 0.6666666666666666,
        "HeisenbergError": 0.2222222222222222,
        "HeisenbergAngle": 1.0493189145752915,
        "EffectiveScore": 0.5846496184619806
    },
    {
        "username": "FP8",
        "userAge": 23,
        "usergender": "male",
        "inputtechnique": "BareHandIntenSelect",
        "radius": 0.21,
        "distance": 0.75,
        "spacing": 0.7,
        "clickDuration": 1.1706380626666668,
        "isCorrect": 1.0,
        "HeisenbergError": 0.0,
        "HeisenbergAngle": 1.2932437618282224,
        "EffectiveScore": 0.8542349953341171
    },
    {
        "username": "FP8",
        "userAge": 23,
        "usergender": "male",
        "inputtechnique": "BareHandIntenSelect",
        "radius": 0.21,
        "distance": 0.75,
        "spacing": 0.3,
        "clickDuration": 1.1559952571,
        "isCorrect": 0.6,
        "HeisenbergError": 0.3,
        "HeisenbergAngle": 0.7354677625296373,
        "EffectiveScore": 0.5190332713865942
    },
    {
        "username": "FP8",
        "userAge": 23,
        "usergender": "male",
        "inputtechnique": "BareHandIntenSelect",
        "radius": 0.21,
        "distance": 0.75,
        "spacing": 0.3,
        "clickDuration": 1.3596029250000001,
        "isCorrect": 0.75,
        "HeisenbergError": 0.125,
        "HeisenbergAngle": 0.6320035031420277,
        "EffectiveScore": 0.551631646423532
    },
    {
        "username": "FP8",
        "userAge": 23,
        "usergender": "male",
        "inputtechnique": "BareHandIntenSelect",
        "radius": 0.21,
        "distance": 0.75,
        "spacing": 0.5,
        "clickDuration": 1.2237782863333333,
        "isCorrect": 0.6666666666666666,
        "HeisenbergError": 0.2222222222222222,
        "HeisenbergAngle": 1.5723650607757447,
        "EffectiveScore": 0.5447609866196625
    },
    {
        "username": "FP8",
        "userAge": 23,
        "usergender": "male",
        "inputtechnique": "BareHandIntenSelect",
        "radius": 0.21,
        "distance": 0.75,
        "spacing": 0.7,
        "clickDuration": 1.015660877,
        "isCorrect": 0.75,
        "HeisenbergError": 0.0,
        "HeisenbergAngle": 0.8131508377425244,
        "EffectiveScore": 0.7384354531950728
    },
    {
        "username": "FP9",
        "userAge": 27,
        "usergender": "male",
        "inputtechnique": "BareHandIntenSelect",
        "radius": 0.21,
        "distance": 0.75,
        "spacing": 0.7,
        "clickDuration": 1.2124490449999998,
        "isCorrect": 1.0,
        "HeisenbergError": 0.0,
        "HeisenbergAngle": 0.4086090600604338,
        "EffectiveScore": 0.8247769290791104
    },
    {
        "username": "FP9",
        "userAge": 27,
        "usergender": "male",
        "inputtechnique": "BareHandIntenSelect",
        "radius": 0.21,
        "distance": 0.75,
        "spacing": 0.3,
        "clickDuration": 1.6206940755555557,
        "isCorrect": 0.6666666666666666,
        "HeisenbergError": 0.3333333333333333,
        "HeisenbergAngle": 0.29680770642806803,
        "EffectiveScore": 0.4113463957953575
    },
    {
        "username": "FP9",
        "userAge": 27,
        "usergender": "male",
        "inputtechnique": "BareHandIntenSelect",
        "radius": 0.21,
        "distance": 0.75,
        "spacing": 0.5,
        "clickDuration": 1.6095379783333332,
        "isCorrect": 1.0,
        "HeisenbergError": 0.0,
        "HeisenbergAngle": 0.30086064301058174,
        "EffectiveScore": 0.6212963058103754
    },
    {
        "username": "FP9",
        "userAge": 27,
        "usergender": "male",
        "inputtechnique": "BareHandIntenSelect",
        "radius": 0.21,
        "distance": 0.75,
        "spacing": 0.5,
        "clickDuration": 1.0124503515,
        "isCorrect": 0.75,
        "HeisenbergError": 0.25,
        "HeisenbergAngle": 0.47071073830572685,
        "EffectiveScore": 0.7407770651556734
    },
    {
        "username": "FP9",
        "userAge": 27,
        "usergender": "male",
        "inputtechnique": "BareHandIntenSelect",
        "radius": 0.21,
        "distance": 0.75,
        "spacing": 0.7,
        "clickDuration": 1.1273210951666668,
        "isCorrect": 1.0,
        "HeisenbergError": 0.0,
        "HeisenbergAngle": 1.359664822534653,
        "EffectiveScore": 0.887058713162958
    },
    {
        "username": "FP9",
        "userAge": 27,
        "usergender": "male",
        "inputtechnique": "BareHandIntenSelect",
        "radius": 0.21,
        "distance": 0.75,
        "spacing": 0.3,
        "clickDuration": 1.4065751974999998,
        "isCorrect": 0.75,
        "HeisenbergError": 0.0,
        "HeisenbergAngle": 0.2309932953600311,
        "EffectiveScore": 0.5332100276849934
    },
    {
        "username": "FP9",
        "userAge": 27,
        "usergender": "male",
        "inputtechnique": "BareHandIntenSelect",
        "radius": 0.21,
        "distance": 0.75,
        "spacing": 0.5,
        "clickDuration": 1.7071869279999998,
        "isCorrect": 0.6,
        "HeisenbergError": 0.3,
        "HeisenbergAngle": 0.8126835982212899,
        "EffectiveScore": 0.3514553621277494
    },
    {
        "username": "FP9",
        "userAge": 27,
        "usergender": "male",
        "inputtechnique": "BareHandIntenSelect",
        "radius": 0.21,
        "distance": 0.75,
        "spacing": 0.3,
        "clickDuration": 1.545352229,
        "isCorrect": 0.6,
        "HeisenbergError": 0.2,
        "HeisenbergAngle": 0.3095359451159657,
        "EffectiveScore": 0.38826099884572013
    },
    {
        "username": "FP9",
        "userAge": 27,
        "usergender": "male",
        "inputtechnique": "BareHandIntenSelect",
        "radius": 0.21,
        "distance": 0.75,
        "spacing": 0.7,
        "clickDuration": 1.0849214905555558,
        "isCorrect": 0.6666666666666666,
        "HeisenbergError": 0.2222222222222222,
        "HeisenbergAngle": 0.48673721898752853,
        "EffectiveScore": 0.6144837875091649
    }
]